setup.py
NBFS/NBFS.py
NBFS/__init__.py
NBFS.egg-info/PKG-INFO
NBFS.egg-info/SOURCES.txt
NBFS.egg-info/dependency_links.txt
NBFS.egg-info/top_level.txt
NBFS/lib/__init__.py
NBFS/lib/attributes.py
NBFS/lib/base.py
NBFS/lib/constants.py
NBFS/lib/datatypes.py
NBFS/lib/decoder.py
NBFS/lib/dictionary.py
NBFS/lib/elements.py
NBFS/lib/html_parser.py
NBFS/lib/text.py
NBFS/lib/utils.py
NBFS/lib/xml_parser.py