Metadata-Version: 1.0
Name: NBFS
Version: 0.0.5
Summary: a tool for analysis NBFS protocol
Home-page: https://github.com/hero576/pynbfs
Author: hero576
Author-email: 812041531@qq.com
License: UNKNOWN
Keywords: NBFS
Platform: any
